{
  "basics": {
    "name": "Alejandro Debus",
    "label": "Machine Learning Engineer",
    "image": "",
    "email": "aledebus@gmail.com",
    "phone": "",
    "url": "https://alejandrodebus.github.io/",
    "summary": "A passionate machine learning engineer with experience in a wide range of areas within this fascinating field.",
    "location": {
      "address": "",
      "postalCode": "",
      "city": "Argentina",
      "countryCode": "AR",
      "region": ""
    },
    "profiles": [
      {
        "network": "Twitter",
        "username": "AlbertEinstein",
        "url": "https://twitter.com/AlbertEinstein"
      }
    ]
  },
  "work": [
    {
      "name": "Kueski",
      "position": "  L3 Machine Learning Engineer",
      "url": "https://kueskipay.com",
      "startDate": "24-02-01",
      "endDate": "-",
      "summary": "Machine learning",
      "highlights": ["IA", "Machine Learning", "MLOps"]
    },
    {
      "name": "Kueski",
      "position": "  L2 Machine Learning Engineer",
      "url": "https://kueskipay.com",
      "startDate": "21-08-23",
      "endDate": "24-01-31",
      "summary": "Machine learning",
      "highlights": ["IA", "Machine Learning", "MLOps"]
    },
    {
      "name": "Universidad de Buenos Aires",
      "position": "  Professor @ Deep Learning Course",
      "url": "https://kueskipay.com",
      "startDate": "21-10-01",
      "endDate": "22-12-31",
      "summary": "Deep learning",
      "highlights": []
    },
    {
      "name": "Mercado Libre",
      "position": "  Sr Data Scientist",
      "url": "https://mercadolibre.com",
      "startDate": "20-06-03",
      "endDate": "21-08-06",
      "summary": "Machine learning",
      "highlights": ["IA", "Machine Learning", "MLOps"]
    },
    {
      "name": "Mercado Libre",
      "position": "  Ssr Data Scientist",
      "url": "https://mercadolibre.com",
      "startDate": "19-06-03",
      "endDate": "20-08-31",
      "summary": "Machine learning",
      "highlights": ["IA", "Machine Learning", "MLOps"]
    },
    {
      "name": "Eiwa",
      "position": "Data Scientist",
      "url": "https://eiwa.ag",
      "startDate": "18-11-18",
      "endDate": "19-05-31",
      "summary": "Machine learning",
      "highlights": ["IA", "Machine Learning", "Computer vision"]
    },
    {
      "name": "Serfe",
      "position": "Web Developer",
      "url": "https://serfe.com",
      "startDate": "18-11-18",
      "endDate": "19-05-31",
      "summary": "Machine learning",
      "highlights": ["IA", "Machine Learning", "Computer vision"]
    }
  ],
  "education": [
    {
      "institution": "Universidad Nacional del Litoral",
      "location": "Santa Fe, Argentina",
      "url": "https://www.fich.unl.edu.ar",
      "area": "Informatics Engineering",
      "studyType": "Eng",
      "startDate": "1905-01-01",
      "endDate": "1905-01-01",
      "score": "10",
      "courses": ["Calculus", "Linear Algrebra", "Programming", "Statistics", "Physics", "Computational Intelligence", "Digital Signal Processing", "Digital Image Processing", "Computational Mechanics", "Computer Graphics", "Networks", "Robotics"]
    }
  ],
  "certificates": [
    {
      "name": "Machine Learning",
      "date": "2018-01-01",
      "issuer": "Stanford University",
      "url": "https://example.com",
      "icon": "fa-solid fa-location-dot"
    },
    {
      "name": "Quantum Computing",
      "date": "2018-01-01",
      "issuer": "Stanford University",
      "url": "https://example.com",
      "icon": "fa-solid fa-tag"
    },
    {
      "name": "Quantum Information",
      "date": "2018-01-01",
      "issuer": "Stanford University",
      "url": "https://example.com",
      "icon": "fa-solid fa-envelope"
    },
    {
      "name": "Quantum Cryptography",
      "date": "2018-01-01",
      "issuer": "Stanford University",
      "url": "https://example.com",
      "icon": "fa-solid fa-hashtag"
    },
    {
      "name": "Quantum Communication",
      "date": "2018-01-01",
      "issuer": "Stanford University",
      "url": "https://example.com",
      "icon": "fa-solid fa-calendar"
    },
    {
      "name": "Quantum Teleportation",
      "date": "2018-01-01",
      "issuer": "Stanford University",
      "url": "https://example.com",
      "icon": "fa-solid fa-clipboard-check"
    }
  ],
  "publications": [
    {
      "name": "Zur Elektrody/namik bewegter Körper",
      "publisher": "Annalen der Physik",
      "releaseDate": "1905-06-30",
      "url": "https://en.wikisource.org/wiki/Translation:On_the_Electrodynamics_of_Moving_Bodies",
      "summary": "It concerned an interpretation of the Michelson–Morley experiment and the properties of light and time. Special relativity incorporates the principle that the speed of light is the same for all inertial observers regardless of the state of motion of the source."
    },
    {
      "name": "Über einen die Erzeugung und Verwandlung des Lichtes betreffenden heuristischen Gesichtspunkt",
      "publisher": "Annalen der Physik",
      "releaseDate": "1905-03-18",
      "url": "https://de.wikisource.org/wiki/Über_einen_die_Erzeugung_und_Verwandlung_des_Lichtes_betreffenden_heuristischen_Gesichtspunkt",
      "summary": "In the second paper, he applied the quantum theory to light to explain the photoelectric effect. In particular, he used the idea of light quanta (photons) to explain experimental results, but stressed the importance of the experimental results. The importance of his work on the photoelectric effect earned him the Nobel Prize in Physics in 1921."
    },
    {
      "name": "Die Grundlage der allgemeinen Relativitätstheorie",
      "publisher": "Annalen der Physik",
      "releaseDate": "1916-03-20",
      "url": "https://de.wikisource.org/wiki/Die_Grundlage_der_allgemeinen_Relativitätstheorie",
      "summary": "The publication of the theory of general relativity made him internationally famous. He was professor of physics at the universities of Zurich (1909–1911) and Prague (1911–1912), before he returned to ETH Zurich (1912–1914)."
    }
  ],
  "skills": [
    {
      "name": "Physics",
      "level": "Master",
      "icon": "fa-solid fa-hashtag",
      "keywords": [
        "Quantum Mechanics",
        "Quantum Computing",
        "Quantum Information",
        "Quantum Cryptography",
        "Quantum Communication",
        "Quantum Teleportation"
      ]
    }
  ],
  "languages": [
    {
      "language": "Spanish",
      "fluency": "Native speaker",
      "icon": ""
    },
    {
      "language": "English",
      "fluency": "Fluent",
      "icon": ""
    }
  ],
  "interests": [
    {
      "name": "Physics",
      "icon": "fa-solid fa-tag",
      "keywords": [
        "Quantum Mechanics",
        "Quantum Computing",
        "Quantum Information",
        "Quantum Cryptography",
        "Quantum Communication",
        "Quantum Teleportation"
      ]
    }
  ],
  "references": [
    {
      "name": "Professor John Doe",
      "icon": "fa-solid fa-laptop",
      "reference": "Lorem ipsum dolor sit amet, consectetur adipiscing elit. Aliquam condimentum, diam quis convallis euismod, arcu mi ullamcorper lorem, a vestibulum nunc magna at sem. Sed in risus ac felis varius blandit. D"
    },
    {
      "name": "Professor John Doe",
      "icon": "fa-solid fa-thumbtack",
      "reference": "Lorem ipsum dolor sit amet, consectetur adipiscing elit. Aliquam condimentum, diam quis convallis euismod, arcu mi ullamcorper lorem, a vestibulum nunc magna at sem. Sed in risus ac felis varius blandit. D"
    }
  ],
  "projects": [
    {
      "name": "Quantum Computing",
      "summary": "Quantum computing is the use of quantum-mechanical phenomena such as superposition and entanglement to perform computation. Computers that perform quantum computations are known as quantum computers.",
      "highlights": ["Quantum Teleportation", "Quantum Cryptography"],
      "startDate": "2018-01-01",
      "endDate": "2018-01-01",
      "url": "https://example.com"
    }
  ]
}
